.hgignore
.hgtags
.travis.yml
CHANGES.md
COPYING
COPYING.LESSER
README.ipynb
README.md
appveyor.yml
requirements.setup.txt
requirements.test.txt
requirements.txt
setup.py
tox.ini
zetup.ini
nodely/__init__.py
nodely/bin.py
nodely/error.py
nodely/setup_keywords.py
nodely/zetup_config.py
nodely.egg-info/PKG-INFO
nodely.egg-info/SOURCES.txt
nodely.egg-info/dependency_links.txt
nodely.egg-info/entry_points.txt
nodely.egg-info/requires.txt
nodely.egg-info/top_level.txt
test/conftest.py
test/setup.py
test/setup_keywords.robot
test/test_nodely.py
test/test_nodely_bin.py
test/test_setup_keywords.py
test/variables.py